CLASSIFIERS
HISTORY.rst
LICENSE.txt
MANIFEST.in
NOTICE.txt
README.rst
setup.py
versioneer.py
/Users/ali/_dev/libcrm114/lib/crm114_base.c
/Users/ali/_dev/libcrm114/lib/crm114_bit_entropy.c
/Users/ali/_dev/libcrm114/lib/crm114_datalib.c
/Users/ali/_dev/libcrm114/lib/crm114_fast_substring_compression.c
/Users/ali/_dev/libcrm114/lib/crm114_hyperspace.c
/Users/ali/_dev/libcrm114/lib/crm114_markov.c
/Users/ali/_dev/libcrm114/lib/crm114_markov_microgroom.c
/Users/ali/_dev/libcrm114/lib/crm114_matrix.c
/Users/ali/_dev/libcrm114/lib/crm114_matrix_util.c
/Users/ali/_dev/libcrm114/lib/crm114_pca.c
/Users/ali/_dev/libcrm114/lib/crm114_pca_lib_fncts.c
/Users/ali/_dev/libcrm114/lib/crm114_regex_tre.c
/Users/ali/_dev/libcrm114/lib/crm114_strnhash.c
/Users/ali/_dev/libcrm114/lib/crm114_svm.c
/Users/ali/_dev/libcrm114/lib/crm114_svm_lib_fncts.c
/Users/ali/_dev/libcrm114/lib/crm114_svm_quad_prog.c
/Users/ali/_dev/libcrm114/lib/crm114_util.c
/Users/ali/_dev/libcrm114/lib/crm114_vector_tokenize.c
include/crm114_config.h
include/crm114_datalib.h
include/crm114_internal.h
include/crm114_lib.h
include/crm114_matrix.h
include/crm114_matrix_util.h
include/crm114_pca.h
include/crm114_pca_lib_fncts.h
include/crm114_regex.h
include/crm114_structs.h
include/crm114_svm.h
include/crm114_svm_lib_fncts.h
include/crm114_svm_quad_prog.h
include/crm114_sysincludes.h
include/fmemopen.h
include/memstream.h
lib/crm114_base.c
lib/crm114_bit_entropy.c
lib/crm114_datalib.c
lib/crm114_fast_substring_compression.c
lib/crm114_hyperspace.c
lib/crm114_markov.c
lib/crm114_markov_microgroom.c
lib/crm114_matrix.c
lib/crm114_matrix_util.c
lib/crm114_pca.c
lib/crm114_pca_lib_fncts.c
lib/crm114_regex_tre.c
lib/crm114_statboost.c
lib/crm114_strnhash.c
lib/crm114_svm.c
lib/crm114_svm_lib_fncts.c
lib/crm114_svm_quad_prog.c
lib/crm114_util.c
lib/crm114_vector_tokenize.c
lib/fmemopen.c
lib/memstream.c
lib/old_crm114_hyperspace.c
pycrm114/__init__.py
pycrm114/_version.py
pycrm114/core.py
pycrm114/errors.py
pycrm114.egg-info/PKG-INFO
pycrm114.egg-info/SOURCES.txt
pycrm114.egg-info/dependency_links.txt
pycrm114.egg-info/requires.txt
pycrm114.egg-info/top_level.txt
