Metadata-Version: 1.1
Name: pycrm114
Version: 0.2.3
Summary: Python interface to libcrm114
Home-page: https://github.com/alisaifee/pycrm114
Author: Ali-Akber Saifee
Author-email: ali at indydevs.org
License: Copyright (c) 2015 Ali-Akber Saifee 
